spmf/__init__.py
spmf-1.4.dist-info/LICENSE
spmf-1.4.dist-info/METADATA
spmf-1.4.dist-info/WHEEL
spmf-1.4.dist-info/top_level.txt
spmf-1.4.dist-info/RECORD
