Metadata-Version: 2.1
Name: spmf
Version: 1.4
Summary: Python Wrapper for SPMF
Home-page: https://github.com/lolei/spmf-py
Author: Lorenz Leitner
Author-email: lrnz.ltnr@gmail.com
License: UNKNOWN
Platform: UNKNOWN
Classifier: Programming Language :: Python :: 3.8
Classifier: License :: OSI Approved :: GNU General Public License v3 (GPLv3)
Classifier: Operating System :: OS Independent
Requires-Python: >=3
License-File: LICENSE
